paloalto_xapi_wrapper/__init__.py
paloalto_xapi_wrapper/xapi_wrapper.py
paloalto_xapi_wrapper-0.1.7.dist-info/WHEEL
paloalto_xapi_wrapper-0.1.7.dist-info/METADATA
paloalto_xapi_wrapper-0.1.7.dist-info/RECORD
