Metadata-Version: 2.1
Name: paloalto-xapi-wrapper
Version: 0.1.7
Summary: Xapi wrapper for quick use
Author: Thomas Christory
Author-email: thomas@christory.net
Requires-Python: >=3.9,<4.0
Classifier: Programming Language :: Python :: 3
Classifier: Programming Language :: Python :: 3.9
Classifier: Programming Language :: Python :: 3.10
Classifier: Programming Language :: Python :: 3.11
Requires-Dist: paloalto-env
Requires-Dist: pan-python
